tracardi_weather/plugin.py
tracardi_weather/model/configuration.py
tracardi_weather/model/__pycache__/configuration.cpython-38.pyc
tracardi_weather/service/weather_client.py
tracardi_weather/service/__pycache__/weather_client.cpython-38.pyc
tracardi_weather/test/manual/test_plugin_weather.py
tracardi_weather-0.6.1.dist-info/LICENSE.md
tracardi_weather-0.6.1.dist-info/METADATA
tracardi_weather-0.6.1.dist-info/WHEEL
tracardi_weather-0.6.1.dist-info/top_level.txt
tracardi_weather-0.6.1.dist-info/RECORD
